aworda/rainfer/__init__.py
aworda/rainfer/adapter/__init__.py
aworda/rainfer/adapter/forward.py
aworda/rainfer/adapter/reverse.py
aworda/rainfer/adapter/util.py
aworda/rainfer/app.py
aworda/rainfer/context.py
aworda/rainfer/dispatcher.py
aworda/rainfer/entry/__init__.py
aworda/rainfer/entry/event.py
aworda/rainfer/entry/message.py
aworda/rainfer/event/__init__.py
aworda/rainfer/event/lifecycle.py
aworda/rainfer/event/message.py
aworda/rainfer/event/mirai.py
aworda/rainfer/exception.py
aworda/rainfer/message/__init__.py
aworda/rainfer/message/chain.py
aworda/rainfer/message/chainsaw.py
aworda/rainfer/message/chainx.py
aworda/rainfer/message/commander/__init__.py
aworda/rainfer/message/commander/saya.py
aworda/rainfer/message/element.py
aworda/rainfer/message/formatter.py
aworda/rainfer/message/parser/__init__.py
aworda/rainfer/message/parser/base.py
aworda/rainfer/message/parser/twilight.py
aworda/rainfer/message/parser/util.py
aworda/rainfer/model.py
aworda/rainfer/typing.py
aworda/rainfer/util/__init__.py
aworda/rainfer/util/async_exec.py
aworda/rainfer/util/cooldown.py
aworda/rainfer/util/interrupt.py
aworda/rainfer/util/send.py
aworda/rainfer/util/validator.py
aworda_rainfer-0.0.1.dist-info/LICENSE
aworda_rainfer-0.0.1.dist-info/WHEEL
aworda_rainfer-0.0.1.dist-info/METADATA
aworda_rainfer-0.0.1.dist-info/RECORD
