Metadata-Version: 2.1
Name: aworda-rainfer
Version: 0.0.1
Summary: Modified from Ariadne & Another elegant Python QQ Bot framework for mirai and mirai-api-http v2.
Home-page: https://github.com/AwordaProject/Rainfer
Keywords: graia,bot,qq,framework,mirai
Author: LinNian
Author-email: crynian@outlook.com
Requires-Python: >=3.8,<4.0
Classifier: Development Status :: 4 - Beta
Classifier: Framework :: AsyncIO
Classifier: Framework :: Robot Framework :: Library
Classifier: Operating System :: OS Independent
Classifier: Programming Language :: Python :: 3
Classifier: Programming Language :: Python :: 3.10
Classifier: Programming Language :: Python :: 3.8
Classifier: Programming Language :: Python :: 3.9
Classifier: Topic :: Communications :: Chat
Classifier: Typing :: Typed
Provides-Extra: full
Provides-Extra: graia
Provides-Extra: server
Provides-Extra: standard
Requires-Dist: aiohttp (>=3.7.4,<4.0.0)
Requires-Dist: fastapi (>=0.74.1,<1.0.0); extra == "server" or extra == "full"
Requires-Dist: graia-broadcast (>=0.16.1,<0.17.0)
Requires-Dist: graia-saya (>=0.0,<0.1); extra == "graia" or extra == "standard" or extra == "full"
Requires-Dist: graia-scheduler (>=0.0,<0.1); extra == "graia" or extra == "standard" or extra == "full"
Requires-Dist: loguru (>=0.6,<0.7)
Requires-Dist: prompt-toolkit (>=3.0.24,<4.0.0); extra == "standard" or extra == "full"
Requires-Dist: pydantic (>=1.8.2,<2.0.0)
Requires-Dist: typing-extensions (>=4.0,<5.0)
Requires-Dist: uvicorn[standard] (>=0.17.5,<0.18.0); extra == "server" or extra == "full"
Requires-Dist: yarl (>=1.7,<2.0)
Project-URL: Documentation, https://graia.rtfd.io/
Project-URL: Repository, https://github.com/AwordaProject/Rainfer
